{
  "$schema": "https://design-tokens.github.io/community-group/format/",
  "$description": "METIS design tokens — OKLch color space. Light values are defaults; dark overrides in $extensions.dark.",
  "color": {
    "background": {
      "$value": "oklch(0.985 0.01 245)",
      "$type": "color",
      "$extensions": { "dark": "oklch(0.16 0.022 250)" }
    },
    "foreground": {
      "$value": "oklch(0.22 0.018 248)",
      "$type": "color",
      "$extensions": { "dark": "oklch(0.95 0.008 235)" }
    },
    "card": {
      "$value": "oklch(0.992 0.008 240)",
      "$type": "color",
      "$extensions": { "dark": "oklch(0.2 0.022 245)" }
    },
    "card-foreground": {
      "$value": "oklch(0.2 0.018 248)",
      "$type": "color",
      "$extensions": { "dark": "oklch(0.95 0.008 235)" }
    },
    "popover": {
      "$value": "oklch(0.992 0.008 240)",
      "$type": "color",
      "$extensions": { "dark": "oklch(0.2 0.022 245)" }
    },
    "popover-foreground": {
      "$value": "oklch(0.2 0.018 248)",
      "$type": "color",
      "$extensions": { "dark": "oklch(0.95 0.008 235)" }
    },
    "primary": {
      "$value": "oklch(0.57 0.11 214)",
      "$type": "color",
      "$extensions": { "dark": "oklch(0.72 0.11 205)" }
    },
    "primary-foreground": {
      "$value": "oklch(0.98 0.006 250)",
      "$type": "color",
      "$extensions": { "dark": "oklch(0.18 0.02 244)" }
    },
    "secondary": {
      "$value": "oklch(0.95 0.015 235)",
      "$type": "color",
      "$extensions": { "dark": "oklch(0.25 0.02 242)" }
    },
    "secondary-foreground": {
      "$value": "oklch(0.28 0.025 244)",
      "$type": "color",
      "$extensions": { "dark": "oklch(0.93 0.008 235)" }
    },
    "muted": {
      "$value": "oklch(0.95 0.014 235)",
      "$type": "color",
      "$extensions": { "dark": "oklch(0.24 0.018 242)" }
    },
    "muted-foreground": {
      "$value": "oklch(0.48 0.03 240)",
      "$type": "color",
      "$extensions": { "dark": "oklch(0.73 0.02 232)" }
    },
    "accent": {
      "$value": "oklch(0.9 0.035 205)",
      "$type": "color",
      "$extensions": { "dark": "oklch(0.3 0.03 205)" }
    },
    "accent-foreground": {
      "$value": "oklch(0.27 0.03 244)",
      "$type": "color",
      "$extensions": { "dark": "oklch(0.95 0.008 235)" }
    },
    "destructive": {
      "$value": "oklch(0.577 0.245 27.325)",
      "$type": "color",
      "$extensions": { "dark": "oklch(0.704 0.191 22.216)" }
    },
    "border": {
      "$value": "oklch(0.89 0.012 240)",
      "$type": "color",
      "$extensions": { "dark": "oklch(1 0 0 / 9%)" }
    },
    "input": {
      "$value": "oklch(0.91 0.014 238)",
      "$type": "color",
      "$extensions": { "dark": "oklch(1 0 0 / 10%)" }
    },
    "ring": {
      "$value": "oklch(0.67 0.1 214)",
      "$type": "color",
      "$extensions": { "dark": "oklch(0.72 0.11 205)" }
    },
    "chart-1": {
      "$value": "oklch(0.62 0.11 214)",
      "$type": "color",
      "$extensions": { "dark": "oklch(0.72 0.11 205)" }
    },
    "chart-2": {
      "$value": "oklch(0.65 0.08 191)",
      "$type": "color",
      "$extensions": { "dark": "oklch(0.68 0.09 185)" }
    },
    "chart-3": {
      "$value": "oklch(0.72 0.14 82)",
      "$type": "color",
      "$extensions": { "dark": "oklch(0.76 0.15 82)" }
    },
    "chart-4": {
      "$value": "oklch(0.68 0.12 52)",
      "$type": "color",
      "$extensions": { "dark": "oklch(0.72 0.13 56)" }
    },
    "chart-5": {
      "$value": "oklch(0.58 0.08 160)",
      "$type": "color",
      "$extensions": { "dark": "oklch(0.66 0.08 160)" }
    },
    "sidebar": {
      "$value": "oklch(0.975 0.008 244)",
      "$type": "color",
      "$extensions": { "dark": "oklch(0.18 0.024 247)" }
    },
    "sidebar-foreground": {
      "$value": "oklch(0.2 0.018 248)",
      "$type": "color",
      "$extensions": { "dark": "oklch(0.95 0.008 235)" }
    },
    "sidebar-primary": {
      "$value": "oklch(0.57 0.11 214)",
      "$type": "color",
      "$extensions": { "dark": "oklch(0.72 0.11 205)" }
    },
    "sidebar-primary-foreground": {
      "$value": "oklch(0.98 0.006 250)",
      "$type": "color",
      "$extensions": { "dark": "oklch(0.16 0.022 250)" }
    },
    "sidebar-accent": {
      "$value": "oklch(0.92 0.028 208)",
      "$type": "color",
      "$extensions": { "dark": "oklch(0.28 0.03 205)" }
    },
    "sidebar-accent-foreground": {
      "$value": "oklch(0.24 0.03 244)",
      "$type": "color",
      "$extensions": { "dark": "oklch(0.95 0.008 235)" }
    },
    "sidebar-border": {
      "$value": "oklch(0.88 0.012 240)",
      "$type": "color",
      "$extensions": { "dark": "oklch(1 0 0 / 8%)" }
    },
    "sidebar-ring": {
      "$value": "oklch(0.67 0.1 214)",
      "$type": "color",
      "$extensions": { "dark": "oklch(0.72 0.11 205)" }
    }
  },
  "radius": {
    "base": {
      "$value": "1rem",
      "$type": "dimension"
    }
  }
}
